<item>
<title>[COLOR red]Derribad al hombre[/COLOR]</title>
<urlsolve>https://drive.google.com/file/d/1AkX6DfVXdN4XCyaI8LesCpqsZBbiYCBV/view</urlsolve>
<info>En Easter Cove, un pueblo pesquero remoto en la costa rocosa de Maine. En este pequeño pueblo, los lazos son profundos como el océano y los secretos son tan densos como la niebla de la mañana. Cada día, multitud de hombres van a la mar a por su pesca diaria mientras que un puñado de mujeres sirven como las como operadoras poderosas, aunque discretas, de la comunidad. Mary Margaret Connolly (Linda Shary), una querida e íntegra matriarca de la ciudad, acaba de morir. A raíz de su muerte, sus hijas, Mary Beth (Morgan Saylor) and Priscilla (Sophie Lowe), se enfrentan a un futuro incierto, perseguidas por las facturas y las deudas olvidadas. Priscilla intenta ocupar el lugar de su madre, encargándose de la pescadería familiar mientras que su hermana menor Mary Beth se niega a aceptar sus responsabilidades. Las hermanas se encuentran en desacuerdo y Mary Beth defiende obstinadamente su sueño de abandonar la ciudad, incluso si eso significa abandonar a Priscilla. Pero tendrá que acudir a su hermana cuando cometa en un gran error.</info>
<date>2019</date>
<thumbnail>https://mejortorrentt.es/elite_pics/derribad-al-hombre-(2020).jpg</thumbnail>
<fanart>https://i.blogs.es/da31cc/critica-derribad-al-hombre-2/450_1000.jpeg</fanart>
</item>
<item>
<title>[COLOR red]Downton abbey 4K UHD[/COLOR]</title>
<urlsolve>https://drive.google.com/file/d/1RCnEx_siOtMxn5b5f1X4QHGRe-6x24kQ/view</urlsolve>
<info>(aquí información del capitulo)</info>
<date>2008</date>
<thumbnail>https://www.avforums.com/attachments/da4k_temp-jpg.1189246/?temp_hash=4e98be0b228d37b44a8f793001cd504c</thumbnail>
<fanart>https://i.blogs.es/afb2bf/downton-abbey-pelicula-opinion-2019-espinof/450_1000.jpg</fanart>
</item>
<item>
<title>[COLOR red]Dumbo 4K[/COLOR]</title>
<urlsolve>https://drive.google.com/file/d/16PT1pCljnDNRFX3TCd9zCzD49IFDmAUJ/view</urlsolve>
<info>El dueño de un circo en aprietos contrata a un hombre y sus dos hijos para cuidar de un elefante recién nacido que puede volar, que pronto se convierte en la atracción principal que revitaliza al circo.</info>
<date>2019</date>
<thumbnail>http://www.elche.es/wp-content/uploads/2019/10/Dumbo-Peli%CC%81cula.jpg</thumbnail>
<fanart>https://e.rpp-noticias.io/normal/2019/04/04/283828_774040.jpg</fanart>
</item>
<item>
<title>[COLOR red]El captor (Stockholm)[/COLOR]</title>
<urlsolve>https://drive.google.com/file/d/1QaxKFrHBX-m2q8oswVtxjyr6AEZwq03Q/view</urlsolve>
<info>El exconvicto Lars Nystrom toma rehenes en un banco de Estocolmo y exige que su camarada, todavía preso, sea puesto en libertad. Mientras la tensión aumenta en el recinto, Lars establece un vínculo especial con una de las rehenes.</info>
<date>2018</date>
<thumbnail>https://m.media-amazon.com/images/M/MV5BNWI1OGM1MzItMTgxMy00MDQyLWExNzMtYjdhMjczNDdhMDhkXkEyXkFqcGdeQXVyMjU3NTI0Mg@@._V1_.jpg</thumbnail>
<fanart>https://images-na.ssl-images-amazon.com/images/S/sgp-catalog-images/region_US/0za8m-MDFYA81QY2T-Full-Image_GalleryCover-en-US-1583868044425._UY500_UX667_RI_VOQRd1S4PfN8n81LZsQFUYtzkWcEl0tH_TTW_.jpg</fanart>
</item>
<item>
<title>[COLOR red]El declive[/COLOR]</title>
<urlsolve>https://drive.google.com/file/d/1ftld9v3MNqHWNL3trlyyKEJFQDHetzap/view</urlsolve>
<info>Tras un accidente en un campo de entrenamiento, un grupo de preparacionistas queda atrapado y dividido en una dura lucha por sus vidas.</info>
<date>2020</date>
<thumbnail>https://cinemagavia.es/wp-content/uploads/2020/03/El-Declive.1.jpg</thumbnail>
<fanart>https://cinemagavia.es/wp-content/uploads/2020/03/El-Declive.1.jpg</fanart>
</item>
<item>
<title>[COLOR red]El Sumiller[/COLOR]</title>
<urlsolve>https://drive.google.com/file/d/1L6m2Ktz-eT_j-ervWp9F5QiXWQBmuyU3/view</urlsolve>
<info>Elijah quiere ser sumiller. Su padre, sin embargo, espera que participe en el negocio familiar, el asador más conocido de Memphis.</info>
<date>2020</date>
<thumbnail>https://i.imgur.com/wQI8Tzs.jpg</thumbnail>
<fanart>https://cinemagavia.es/wp-content/uploads/2020/03/El-sumiller.1.jpg</fanart>
</item>
<item>
<title>[COLOR red]Enterrados[/COLOR]</title>
<urlsolve>https://drive.google.com/file/d/1Rk4Dk_Rl3K0s5zoHX-jacvcIpay3E9-E/view</urlsolve>
<info>Tras producirse un gran derrumbe en una mina, Daniel (Joaquín Furriel) queda fortuitamente atrapado junto a un grupo de compañeros en el hueco de una galería a 600 metros de profundidad. No tardan en asimilar que se encuentran solos y que ellos mismos son los que tendrán que poner todos los medios para encontrar una forma de salir.</info>
<date>2018</date>
<thumbnail>https://pics.filmaffinity.com/enterrados-833971387-large.jpg</thumbnail>
<fanart>https://r2.abcimg.es/resizer/resizer.php?imagen=https%3A%2F%2Fstatic3.abc.es%2Fmedia%2Fpeliculas%2F000%2F053%2F118%2Fenterrados-2.jpg</fanart>
</item>
<item>
<title>[COLOR red]En acto de servicio[/COLOR]</title>
<urlsolve>https://drive.google.com/file/d/1fEELaC0VuHbWcs7xSClIjCdTQqSUFAXR/view</urlsolve>
<info>Frank Penny (Aaron Eckhart) es un policía patrullando las calles que, accidentalmente, mata al sospechoso de secuestrar a la hija del jefe de policía. Con la culpa de haber arruinado la única pista que había, Frank comienza una carrera contra el tiempo para intentar salvar a la víctima. </info>
<date>2019</date>
<thumbnail>https://dvdblumarket.com/images/Line%20of%20Duty%20bd.jpg</thumbnail>
<fanart>https://hips.hearstapps.com/hmg-prod.s3.amazonaws.com/images/en-acto-de-servicio-2019-aaron-eckhart-1579430815.jpg?resize=480:*</fanart>
</item>
<item>
<title>[COLOR red]En guerra[/COLOR]</title>
<urlsolve>https://drive.google.com/file/d/1ToqJCIHIx0615wmXol8nPphmhXlat-A8/view</urlsolve>
<info>Hace dos atrás, la fábrica de Perrin, con 1100 empleados, conocida en la industria automovilística y afiliada al grupo alemán Schäfer, firmó un acuerdo para que sus trabajadores aceptaran un recorte salarial, con el fin de salvar a la compañía y prometiendo a cambio proteger sus puestos de trabajo durante al menos cinco años. Pero cuando llega el momento, la compañía toma la decisión de cerrar. Los trabajadores, liderados por Laurent Amédéo (Vincent Lindon), se niegan a aceptarlo e intentan recuperar su trabajo</info>
<date>2018</date>
<thumbnail>https://4.bp.blogspot.com/-MlwgD8uacqM/XLURogYiMUI/AAAAAAAAa_A/5Cj8CMVxtEURvvWcLN5oW_16uB_4ktx4QCK4BGAYYCw/s1600/EL_BAZAR_DEL_ESPECTACULO-15_04_2019_20_19_04-0001-798994.jpeg</thumbnail>
<fanart>https://img.over-blog-kiwi.com/1/49/25/24/20180624/ob_f5cf04_enguerre.jpg</fanart>
</item>
<item>
<title>[COLOR red]El canto del lobo 4K[/COLOR]</title>
<urlsolve>https://drive.google.com/file/d/1yeDtR59BsHSAtVqvw8ARjpMOySMevl-v/view</urlsolve>
<info>Ante una inminente guerra nuclear, un militar experto en acústica submarina debe demostrar con la ayuda de su oído, que las cosas no son como parecen ni como suenan.</info>
<date>2019</date>
<thumbnail>http://image.tmdb.org/t/p/w500/8oSxFcIxBcJqkajoRgEy4byQsBF.jpg</thumbnail>
<fanart>https://assets.fanart.tv/fanart/movies/484468/moviebackground/le-chant-du-loup-5c37a09633505.jpg</fanart>
</item>
<item>
<title>[COLOR red]El faro de las Orcas[/COLOR]</title>
<urlsolve>https://drive.google.com/file/d/1Do-KcfICnOLWbXaKeQu6iYgB1DDDvft-/view</urlsolve>
<info>Lola viaja con su hijo autista, Tristán, hasta la Patagonia para encontrarse con Beto, un guardafauna que tiene una relación muy especial con las orcas salvajes. Tristán ha mostrado una extraña empatía y respuesta de estímulos ante las orcas. La determinación de Lola de luchar por la mejora de su hijo, la peculiar personalidad de Tristán y su relación con la naturaleza harán que la vida de todos ellos cambie para siempre.</info>
<date>2016</date>
<thumbnail>https://http2.mlstatic.com/D_NQ_NP_900525-MLA26725378754_012018-O.jpg</thumbnail>
<fanart>https://i.pinimg.com/originals/d7/44/39/d7443973102f834c3810eb762a6c2b50.jpg</fanart>
</item>
<item>
<title>[COLOR red]El regreso de Aladino[/COLOR]</title>
<urlsolve>https://drive.google.com/file/d/1oMCznVi9DuVNHOVXbvqJEgXgrryNQLlh/view</urlsolve>
<info>Después de liberar a Bagdad de las garras de su terrible visir, Aladin está aburrido en palacio. Todavía no ha decidido pedir matrimonio a la princesa. Pero un terrible dictador, Shah Zaman, se invita al Palacio y anuncia que ha venido a tomar la ciudad y casarse con la Princesa. Aladin no tiene más remedio que huir del Palacio. Intentará recuperar a su antiguo Genio y así, volver para liberar a la ciudad y salvar a su novia.</info>
<date>2018</date>
<thumbnail>https://i.imgur.com/Q6uF4VH.jpg</thumbnail>
<fanart>https://image.tmdb.org/t/p/w780/2Uc19wAkJOA5tgzVyh5x1BUXgYx.jpg</fanart>
</item>
<item>
<title>[COLOR red]El espia que me planto 4K[/COLOR]</title>
<urlsolve>https://drive.google.com/file/d/1f8A_OROLA7zzgaYTLzRN4VfzZIzwJDLs/view</urlsolve>
<info>Audrey y Morgan son dos amigas que se ven involucradas en una aventura llena de peligros cuando el exnovio de Audrey, un espía internacional, irrumpe en sus vidas con un ejército de asesinos pisándole los talones.</info>
<date>2018</date>
<thumbnail>https://hips.hearstapps.com/es.h-cdn.co/fotoes/images/media/imagenes/recursos/cartel-teaser-el-espia-que-me-planto/138088653-1-esl-ES/cartel-teaser-el-espia-que-me-planto.jpg</thumbnail>
<fanart>https://i2.wp.com/noescinetodoloquereluce.com/wp-content/uploads/2018/07/espia.jpg</fanart>
</item>
<item>
<title>[COLOR red]El expreso de medianoche[/COLOR]</title>
<urlsolve>https://drive.google.com/file/d/1D13-jXqR4Pmn13q-YcSgb4sUFqtGFdHL/view</urlsolve>
<info>Billy Hayes, un joven estadounidense, fue detenido en el aeropuerto de Estambul cuando se disponía a subir a un avión con varios paquetes de hachís. Acusado de uno de los delitos considerados más graves en Turquía, Billy es condenado a cuatro años de cárcel. En prisión sufrirá las atrocidades propias de un sistema penitenciario brutal e inhumano.</info>
<date>1978</date>
<thumbnail>https://cdn.compraentradas.com/img/Carteles/expresomedianoche.jpg</thumbnail>
<fanart>https://cdnb.20m.es/sites/127/2018/08/El-expreso-de-medianoche-t-620x412.jpg</fanart>
</item>
<item>
<title>[COLOR red]El niño que domó el viento[/COLOR]</title>
<urlsolve>https://drive.google.com/file/d/1d40rfJQXWXe2RN7KKCbkVYPFn7xn7SEL/view</urlsolve>
<info>Un chico de la República de Malaui decide ayudar a las personas de su pueblo construyendo una turbina después de leer un libro en el que se explican los pasos para su creación. Película basada en el libro homónimo de William Kamkwamba y Bryan Mealer</info>
<date>2019</date>
<thumbnail>http://image.tmdb.org/t/p/w500/kjdYOYNpPTgL9Ll8fVGlTyfbc08.jpg</thumbnail>
<fanart>https://assets.fanart.tv/fanart/movies/491480/moviebackground/the-boy-who-harnessed-the-wind-5c8e3336bf8bd.jpg</fanart>
</item>
<item>
<title>[COLOR red]El ultimo acto[/COLOR]</title>
<urlsolve>https://drive.google.com/file/d/1b8rnMFpH1casVepaKypEVSrhH__f2Qey/view</urlsolve>
<info>El legendario actor Sir Michael Gifford vive recluido en su casa de campo. Desde hace años sufre una enfermedad degenerativa que intenta ocultar al público. ... Hasta que aparece Dorottya, una joven cuidadora húngara, que secretamente aspira a convertirse en actriz.</info>
<date>2018</date>
<thumbnail>https://imgr.cineserie.com/2018/10/1286811.jpg</thumbnail>
<fanart>https://www.startattle.com/wp-content/uploads/2019/03/all-is-true-2018-movie-kenneth-branagh-judi-dench-ian-mckellen.jpg</fanart>
</item>
<item>
<title>[COLOR red]Este niño necesita aire fresco[/COLOR]</title>
<urlsolve>https://drive.google.com/file/d/1YTF93xT04dDXYzJdrJbsg37km53MrpP1/view</urlsolve>
<info>La infancia del famoso humorista Hape Kerkeling está llena de humor, pero al mismo tiempo está marcada por experiencias dolorosas y traumáticas en la República Federal de los años 60 y 70. Desde bien joven intenta entretener a sus compañeros con divertidas parodias, pues se propone hacer reír a todo el mundo tras el suicidio de su madre.</info>
<date>2018</date>
<thumbnail>https://m.guiadelocio.com/var/guiadelocio.com/storage/images/cine/archivo-peliculas/este-nino-necesita-aire-fresco/37924412-2-esl-ES/este-nino-necesita-aire-fresco.jpg</thumbnail>
<fanart>https://todobenicassim.com/wp-content/uploads/2019/10/pelicula_benicasim.jpg</fanart>
</item>
<item>
<title>[COLOR red]Feliz día de tu muerte 2[/COLOR]</title>
<urlsolve>https://drive.google.com/file/d/14CQka4BMj1qLKfhTFDJ_uaOt7vKA8YAT/view</urlsolve>
<info>Dos años después de los eventos acaecidos en la primera película, Tree Gelbman vuelve a entrar en el bucle temporal para descubrir el motivo por el cual accedió a él en primer lugar. También debe hacer frente a Lori, que tras resucitar a causa del buble ha vuelto sedienta de venganza. Secuela de "Happy Death Day" (2017)</info>
<date>2019</date>
<thumbnail>http://image.tmdb.org/t/p/w500/5AgVGF0T41f9mnAvoS3HYdqjJYu.jpg</thumbnail>
<fanart>http://image.tmdb.org/t/p/original/rTFnqSSWreCgRYJ1awI1PLL3dpA.jpg</fanart>
</item>
<item>
<title>[COLOR blue]Frozen 2[/COLOR]</title>
<urlsolve>https://drive.google.com/file/d/1aqMAcwzxnH9toV4V-k71Yb0Y4iU_ITPF/view</urlsolve>
<info>Elsa tiene un poder extraordinario: es capaz de crear hielo y nieve. Sin embargo, a pesar de lo feliz que la hacen los habitantes de Arendelle, siente que no encaja allá. Después de oír una voz misteriosa, Elsa, acompañada por Anna, Kristoff, Olaf y Sven, viaja a los bosques embrujados y los mares oscuros que se extienden más allá de los límites de su reino para descubrir quién es en realidad y por qué posee un poder tan asombroso.</info>
<date>2019</date>
<thumbnail>https://i.imgur.com/vksqnPI.jpg</thumbnail>
<fanart>https://i.imgur.com/MpeP2aD.jpg</fanart>
</item>

